MANIFEST.in
setup.cfg
setup.py
fineart_superset.egg-info/PKG-INFO
fineart_superset.egg-info/SOURCES.txt
fineart_superset.egg-info/dependency_links.txt
fineart_superset.egg-info/not-zip-safe
fineart_superset.egg-info/requires.txt
fineart_superset.egg-info/top_level.txt
superset/__init__.py
superset/cache_util.py
superset/cli.py
superset/config.py
superset/dataframe.py
superset/db_engine_specs.py
superset/extract_table_names.py
superset/import_util.py
superset/jinja_context.py
superset/legacy.py
superset/security.py
superset/sql_lab.py
superset/sql_parse.py
superset/stats_logger.py
superset/utils.py
superset/viz.py
superset/bin/__init__.py
superset/bin/superset
superset/connectors/__init__.py
superset/connectors/base.py
superset/connectors/connector_registry.py
superset/connectors/druid/__init__.py
superset/connectors/druid/models.py
superset/connectors/druid/views.py
superset/connectors/sqla/__init__.py
superset/connectors/sqla/models.py
superset/connectors/sqla/views.py
superset/data/__init__.py
superset/data/birth_france_data_for_country_map.csv
superset/data/birth_names.csv.gz
superset/data/birth_names.json.gz
superset/data/countries.json.gz
superset/data/countries.md
superset/data/countries.py
superset/data/energy.json.gz
superset/data/multiformat_time_series.json.gz
superset/data/random_time_series.json.gz
superset/data/san_francisco.csv.gz
superset/data/unicode_utf8_unixnl_test.csv
superset/db_engines/__init__.py
superset/db_engines/hive.py
superset/db_engines/presto.py
superset/migrations/README
superset/migrations/__init__.py
superset/migrations/alembic.ini
superset/migrations/env.py
superset/migrations/script.py.mako
superset/migrations/versions/1226819ee0e3_fix_wrong_constraint_on_table_columns.py
superset/migrations/versions/1296d28ec131_druid_exports.py
superset/migrations/versions/12d55656cbca_is_featured.py
superset/migrations/versions/18e88e1cc004_making_audit_nullable.py
superset/migrations/versions/1a48a5411020_adding_slug_to_dash.py
superset/migrations/versions/1d2ddd543133_log_dt.py
superset/migrations/versions/1e2841a4128_.py
superset/migrations/versions/2591d77e9831_user_id.py
superset/migrations/versions/27ae655e4247_make_creator_owners.py
