Metadata-Version: 1.1
Name: fineart-superset
Version: 0.18.5
Summary: A interactive data visualization platform build on SqlAlchemy and druid.io
Home-page: https://github.com/fineartdev/superset
Author: FineArt Consulting
Author-email: feng@fineartconsulting.cn
License: UNKNOWN
Download-URL: https://github.com/fineartdev/superset/tarball/0.18.5
Platform: UNKNOWN
Classifier: Programming Language :: Python :: 2.7
Classifier: Programming Language :: Python :: 3.4
Classifier: Programming Language :: Python :: 3.5
